invest_ucm_calibration/__init__.py
invest_ucm_calibration/settings.py
invest_ucm_calibration/cli/__init__.py
invest_ucm_calibration/cli/main.py
invest_ucm_calibration-0.6.0.dist-info/LICENSE
invest_ucm_calibration-0.6.0.dist-info/METADATA
invest_ucm_calibration-0.6.0.dist-info/WHEEL
invest_ucm_calibration-0.6.0.dist-info/entry_points.txt
invest_ucm_calibration-0.6.0.dist-info/top_level.txt
invest_ucm_calibration-0.6.0.dist-info/RECORD
