Metadata-Version: 2.1
Name: invest-ucm-calibration
Version: 0.6.0
Summary: Automated calibration of the InVEST urban cooling model with simulated annealing
Home-page: https://github.com/martibosch/invest-ucm-calibration
Author: Martí Bosch
Author-email: marti.bosch@epfl.ch
License: GPL-3.0
Platform: UNKNOWN
Classifier: License :: OSI Approved :: GNU Lesser General Public License v3 (LGPLv3)
Classifier: Programming Language :: Python
Classifier: Programming Language :: Python :: 3
Classifier: Programming Language :: Python :: 3.8
Classifier: Programming Language :: Python :: 3.9
Classifier: Programming Language :: Python :: 3.10
License-File: LICENSE
Requires-Dist: fire
Requires-Dist: fiona (>=1.0.0)
Requires-Dist: natcap-invest (>=3.10.1)
Requires-Dist: rasterio (>=1.0.0)
Requires-Dist: rioxarray
Requires-Dist: scikit-learn (>=1.0.0)
Requires-Dist: simanneal (>=0.5.0)
Requires-Dist: xarray
Provides-Extra: dev
Requires-Dist: build ; extra == 'dev'
Requires-Dist: bump2version ; extra == 'dev'
Requires-Dist: pre-commit ; extra == 'dev'
Requires-Dist: pytest ; extra == 'dev'
Requires-Dist: pytest-cov ; extra == 'dev'
Requires-Dist: twine ; extra == 'dev'
Provides-Extra: docs
Requires-Dist: sphinx (==5.3.0) ; extra == 'docs'
Requires-Dist: myst-parser (==0.18.1) ; extra == 'docs'
